{
  "version": "7",
  "dialect": "mysql",
  "entries": [
    {
      "idx": 0,
      "version": "5",
      "when": 1771278959698,
      "tag": "0000_condemned_iron_lad",
      "breakpoints": true
    },
    {
      "idx": 1,
      "version": "5",
      "when": 1771279522923,
      "tag": "0001_neat_emma_frost",
      "breakpoints": true
    },
    {
      "idx": 2,
      "version": "5",
      "when": 1771280590329,
      "tag": "0002_jittery_jack_flag",
      "breakpoints": true
    },
    {
      "idx": 3,
      "version": "5",
      "when": 1771322709067,
      "tag": "0003_dazzling_arclight",
      "breakpoints": true
    },
    {
      "idx": 4,
      "version": "5",
      "when": 1771340177975,
      "tag": "0004_parched_the_captain",
      "breakpoints": true
    },
    {
      "idx": 5,
      "version": "5",
      "when": 1771355644086,
      "tag": "0005_futuristic_the_renegades",
      "breakpoints": true
    },
    {
      "idx": 6,
      "version": "5",
      "when": 1771362774258,
      "tag": "0006_uneven_scarecrow",
      "breakpoints": true
    },
    {
      "idx": 7,
      "version": "5",
      "when": 1771367865809,
      "tag": "0007_acoustic_quentin_quire",
      "breakpoints": true
    },
    {
      "idx": 8,
      "version": "5",
      "when": 1771396771480,
      "tag": "0008_slow_mole_man",
      "breakpoints": true
    },
    {
      "idx": 9,
      "version": "5",
      "when": 1771397365170,
      "tag": "0009_dear_rage",
      "breakpoints": true
    },
    {
      "idx": 10,
      "version": "5",
      "when": 1771442221550,
      "tag": "0010_dry_moondragon",
      "breakpoints": true
    },
    {
      "idx": 11,
      "version": "5",
      "when": 1771444596383,
      "tag": "0011_breezy_purifiers",
      "breakpoints": true
    },
    {
      "idx": 12,
      "version": "5",
      "when": 1771493726814,
      "tag": "0012_amusing_garia",
      "breakpoints": true
    },
    {
      "idx": 13,
      "version": "5",
      "when": 1771529507366,
      "tag": "0013_faulty_wallop",
      "breakpoints": true
    },
    {
      "idx": 14,
      "version": "5",
      "when": 1771530548052,
      "tag": "0014_cold_revanche",
      "breakpoints": true
    },
    {
      "idx": 15,
      "version": "5",
      "when": 1771540668685,
      "tag": "0015_keen_spot",
      "breakpoints": true
    },
    {
      "idx": 16,
      "version": "5",
      "when": 1771623210241,
      "tag": "0016_wet_radioactive_man",
      "breakpoints": true
    },
    {
      "idx": 17,
      "version": "5",
      "when": 1771669766387,
      "tag": "0017_mighty_wrecking_crew",
      "breakpoints": true
    },
    {
      "idx": 18,
      "version": "5",
      "when": 1771670865413,
      "tag": "0018_equal_old_lace",
      "breakpoints": true
    },
    {
      "idx": 19,
      "version": "5",
      "when": 1771683076209,
      "tag": "0019_woozy_yellowjacket",
      "breakpoints": true
    },
    {
      "idx": 20,
      "version": "5",
      "when": 1771683611933,
      "tag": "0020_misty_ares",
      "breakpoints": true
    },
    {
      "idx": 21,
      "version": "5",
      "when": 1771698847906,
      "tag": "0021_brown_storm",
      "breakpoints": true
    },
    {
      "idx": 22,
      "version": "5",
      "when": 1771702480568,
      "tag": "0022_spotty_blizzard",
      "breakpoints": true
    },
    {
      "idx": 23,
      "version": "5",
      "when": 1771703113852,
      "tag": "0023_yellow_doctor_faustus",
      "breakpoints": true
    },
    {
      "idx": 24,
      "version": "5",
      "when": 1771706016037,
      "tag": "0024_slow_gwen_stacy",
      "breakpoints": true
    },
    {
      "idx": 25,
      "version": "5",
      "when": 1771792989770,
      "tag": "0025_dark_genesis",
      "breakpoints": true
    },
    {
      "idx": 26,
      "version": "5",
      "when": 1771873546521,
      "tag": "0026_petite_wendigo",
      "breakpoints": true
    },
    {
      "idx": 27,
      "version": "5",
      "when": 1771878354586,
      "tag": "0027_condemned_chameleon",
      "breakpoints": true
    },
    {
      "idx": 28,
      "version": "5",
      "when": 1771882181275,
      "tag": "0028_rainy_whistler",
      "breakpoints": true
    },
    {
      "idx": 29,
      "version": "5",
      "when": 1771882307733,
      "tag": "0029_silent_silver_fox",
      "breakpoints": true
    },
    {
      "idx": 30,
      "version": "5",
      "when": 1771882933222,
      "tag": "0030_uneven_joseph",
      "breakpoints": true
    },
    {
      "idx": 31,
      "version": "5",
      "when": 1771884315365,
      "tag": "0031_shiny_cassandra_nova",
      "breakpoints": true
    },
    {
      "idx": 32,
      "version": "5",
      "when": 1771935402173,
      "tag": "0032_bored_princess_powerful",
      "breakpoints": true
    },
    {
      "idx": 33,
      "version": "5",
      "when": 1771935456110,
      "tag": "0033_wakeful_black_crow",
      "breakpoints": true
    },
    {
      "idx": 34,
      "version": "5",
      "when": 1771936421016,
      "tag": "0034_giant_celestials",
      "breakpoints": true
    },
    {
      "idx": 35,
      "version": "5",
      "when": 1771943856842,
      "tag": "0035_empty_prowler",
      "breakpoints": true
    },
    {
      "idx": 36,
      "version": "5",
      "when": 1771981971950,
      "tag": "0036_lumpy_nekra",
      "breakpoints": true
    },
    {
      "idx": 37,
      "version": "5",
      "when": 1772018660825,
      "tag": "0037_fearless_killmonger",
      "breakpoints": true
    },
    {
      "idx": 38,
      "version": "5",
      "when": 1772144587502,
      "tag": "0038_small_tusk",
      "breakpoints": true
    },
    {
      "idx": 39,
      "version": "5",
      "when": 1772149748198,
      "tag": "0039_redundant_darkhawk",
      "breakpoints": true
    },
    {
      "idx": 40,
      "version": "5",
      "when": 1772306209781,
      "tag": "0040_nebulous_the_stranger",
      "breakpoints": true
    },
    {
      "idx": 41,
      "version": "5",
      "when": 1772312268121,
      "tag": "0041_ancient_squadron_supreme",
      "breakpoints": true
    },
    {
      "idx": 42,
      "version": "5",
      "when": 1772315260879,
      "tag": "0042_brief_brother_voodoo",
      "breakpoints": true
    },
    {
      "idx": 43,
      "version": "5",
      "when": 1772323240209,
      "tag": "0043_eager_manta",
      "breakpoints": true
    },
    {
      "idx": 44,
      "version": "5",
      "when": 1772326974825,
      "tag": "0044_round_ma_gnuci",
      "breakpoints": true
    },
    {
      "idx": 45,
      "version": "5",
      "when": 1772358837457,
      "tag": "0045_broken_captain_marvel",
      "breakpoints": true
    },
    {
      "idx": 46,
      "version": "5",
      "when": 1772395573774,
      "tag": "0046_lovely_kylun",
      "breakpoints": true
    },
    {
      "idx": 47,
      "version": "5",
      "when": 1772726336376,
      "tag": "0047_dizzy_santa_claus",
      "breakpoints": true
    },
    {
      "idx": 48,
      "version": "5",
      "when": 1772789550060,
      "tag": "0048_secret_warpath",
      "breakpoints": true
    },
    {
      "idx": 49,
      "version": "5",
      "when": 1772792463190,
      "tag": "0049_jazzy_mystique",
      "breakpoints": true
    },
    {
      "idx": 50,
      "version": "5",
      "when": 1773013635749,
      "tag": "0050_greedy_secret_warriors",
      "breakpoints": true
    },
    {
      "idx": 51,
      "version": "5",
      "when": 1773015928052,
      "tag": "0051_mature_sentinel",
      "breakpoints": true
    }
  ]
}